odoo/addons/project_portal_task_visibility/README.rst
odoo/addons/project_portal_task_visibility/__init__.py
odoo/addons/project_portal_task_visibility/__manifest__.py
odoo/addons/project_portal_task_visibility/hooks.py
odoo/addons/project_portal_task_visibility/i18n/it.po
odoo/addons/project_portal_task_visibility/i18n/project_portal_task_visibility.pot
odoo/addons/project_portal_task_visibility/readme/CONTRIBUTORS.md
odoo/addons/project_portal_task_visibility/readme/DESCRIPTION.md
odoo/addons/project_portal_task_visibility/security/project_portal_task_security.xml
odoo/addons/project_portal_task_visibility/static/description/icon.png
odoo/addons/project_portal_task_visibility/static/description/index.html
odoo/addons/project_portal_task_visibility/tests/__init__.py
odoo/addons/project_portal_task_visibility/tests/test_hooks.py
odoo_addon_project_portal_task_visibility-18.0.1.0.0.3.dist-info/METADATA
odoo_addon_project_portal_task_visibility-18.0.1.0.0.3.dist-info/WHEEL
odoo_addon_project_portal_task_visibility-18.0.1.0.0.3.dist-info/top_level.txt
odoo_addon_project_portal_task_visibility-18.0.1.0.0.3.dist-info/RECORD
